GifCombiner/GifCombiner.py
GifCombiner/__init__.py
GifCombiner-1.0.1.dist-info/LICENSE
GifCombiner-1.0.1.dist-info/METADATA
GifCombiner-1.0.1.dist-info/WHEEL
GifCombiner-1.0.1.dist-info/top_level.txt
GifCombiner-1.0.1.dist-info/RECORD
